[
  {
    "locationdata_id": "6535b594c1a6ed2da5fed064",
    "locationName": "Old Dog & Partridge",
    "locationCityId": 2,
    "locationCityName": "Nottingham",
    "description": "Beautiful park in the heart of the city.",
    "locationPath": "https://lh5.googleusercontent.com/p/AF1QipO3E7f7sjAQEi2E0rcSeAyGS0Ix_JUyrxXlSg8=w408-h271-k-no",
    "picturePath": "https://lh5.googleusercontent.com/p/AF1QipO3E7f7sjAQEi2E0rcSeAyGS0Ix_JUyrxXlSg8=w408-h271-k-no"
  },
  {
    "locationdata_id": "6535b594c1a6ed2da5fed064",
    "locationName": "Old Dog & Partridge",
    "locationCityId": 2,
    "locationCityName": "Nottingham",
    "description": "Famous museum showcasing art and history.",
    "locationPath": "https://lh5.googleusercontent.com/p/AF1QipO3E7f7sjAQEi2E0rcSeAyGS0Ix_JUyrxXlSg8=w408-h271-k-no",
    "picturePath": "https://lh5.googleusercontent.com/p/AF1QipO3E7f7sjAQEi2E0rcSeAyGS0Ix_JUyrxXlSg8=w408-h271-k-no"
  },
  {
    "locationdata_id": "6535b594c1a6ed2da5fed064",
    "locationName": "Old Dog & Partridge",
    "locationCityId": 2,
    "locationCityName": "Nottingham",
    "description": "Sunny beach with golden sands.",
    "locationPath": "https://lh5.googleusercontent.com/p/AF1QipO3E7f7sjAQEi2E0rcSeAyGS0Ix_JUyrxXlSg8=w408-h271-k-no",
    "picturePath": "https://lh5.googleusercontent.com/p/AF1QipO3E7f7sjAQEi2E0rcSeAyGS0Ix_JUyrxXlSg8=w408-h271-k-no"
  },
  {
    "locationdata_id": "6535b594c1a6ed2da5fed064",
    "locationName": "Old Dog & Partridge",
    "locationCityId": 2,
    "locationCityName": "Nottingham",
    "description": "Spectacular views from the mountain peaks.",
    "locationPath": "https://lh5.googleusercontent.com/p/AF1QipO3E7f7sjAQEi2E0rcSeAyGS0Ix_JUyrxXlSg8=w408-h271-k-no",
    "picturePath": "https://lh5.googleusercontent.com/p/AF1QipO3E7f7sjAQEi2E0rcSeAyGS0Ix_JUyrxXlSg8=w408-h271-k-no"
  },
  {
    "locationdata_id": "6535b594c1a6ed2da5fed064",
    "locationName": "Old Dog & Partridge",
    "locationCityId": 1,
    "locationCityName": "Derby",
    "description": "Ancient ruins from the Roman Empire.",
    "locationPath": "https://lh5.googleusercontent.com/p/AF1QipO3E7f7sjAQEi2E0rcSeAyGS0Ix_JUyrxXlSg8=w408-h271-k-no",
    "picturePath": "https://lh5.googleusercontent.com/p/AF1QipO3E7f7sjAQEi2E0rcSeAyGS0Ix_JUyrxXlSg8=w408-h271-k-no"
  },
  {
    "locationdata_id": "6535b594c1a6ed2da5fed064",
    "locationName": "Old Dog & Partridge",
    "locationCityId": 1,
    "locationCityName": "Derby",
    "description": "Home to a diverse range of animal species.",
    "locationPath": "https://lh5.googleusercontent.com/p/AF1QipO3E7f7sjAQEi2E0rcSeAyGS0Ix_JUyrxXlSg8=w408-h271-k-no",
    "picturePath": "https://lh5.googleusercontent.com/p/AF1QipO3E7f7sjAQEi2E0rcSeAyGS0Ix_JUyrxXlSg8=w408-h271-k-no"
  },
  {
    "locationdata_id": "6535b594c1a6ed2da5fed064",
    "locationName": "Old Dog & Partridge",
    "locationCityId": 1,
    "locationCityName": "Derby",
    "description": "Traditional Japanese garden with bonsai trees.",
    "locationPath": "https://lh5.googleusercontent.com/p/AF1QipO3E7f7sjAQEi2E0rcSeAyGS0Ix_JUyrxXlSg8=w408-h271-k-no",
    "picturePath": "https://lh5.googleusercontent.com/p/AF1QipO3E7f7sjAQEi2E0rcSeAyGS0Ix_JUyrxXlSg8=w408-h271-k-no"
  },
  {
    "locationdata_id": "6535b594c1a6ed2da5fed064",
    "locationName": "Old Dog & Partridge",
    "locationCityId": 1,
    "locationCityName": "Derby",
    "description": "Exciting rides and family-friendly entertainment.",
    "locationPath": "https://lh5.googleusercontent.com/p/AF1QipO3E7f7sjAQEi2E0rcSeAyGS0Ix_JUyrxXlSg8=w408-h271-k-no",
    "picturePath": "https://lh5.googleusercontent.com/p/AF1QipO3E7f7sjAQEi2E0rcSeAyGS0Ix_JUyrxXlSg8=w408-h271-k-no"
  },
  {
    "locationdata_id": "6535b594c1a6ed2da5fed064",
    "locationName": "Old Dog & Partridge",
    "locationCityId": 2,
    "locationCityName": "Nottingham",
    "description": "America's first national park with geothermal wonders.",
    "locationPath": "https://lh5.googleusercontent.com/p/AF1QipO3E7f7sjAQEi2E0rcSeAyGS0Ix_JUyrxXlSg8=w408-h271-k-no",
    "picturePath": "https://lh5.googleusercontent.com/p/AF1QipO3E7f7sjAQEi2E0rcSeAyGS0Ix_JUyrxXlSg8=w408-h271-k-no"
  },
  {
    "locationdata_id": "6535b594c1a6ed2da5fed064",
    "locationName": "Old Dog & Partridge",
    "locationCityId": 2,
    "locationCityName": "Nottingham",
    "description": "Premier destination for skiing and snowboarding.",
    "locationPath": "https://lh5.googleusercontent.com/p/AF1QipO3E7f7sjAQEi2E0rcSeAyGS0Ix_JUyrxXlSg8=w408-h271-k-no",
    "picturePath": "https://lh5.googleusercontent.com/p/AF1QipO3E7f7sjAQEi2E0rcSeAyGS0Ix_JUyrxXlSg8=w408-h271-k-no"
  }
]
